Math/__init__.py
Math/maths.py
markmath-1.0.0.dist-info/licenses/LICENSE
markmath-1.0.0.dist-info/METADATA
markmath-1.0.0.dist-info/WHEEL
markmath-1.0.0.dist-info/top_level.txt
markmath-1.0.0.dist-info/RECORD
